{
    "home.emptyTitle": "ロックがありません。",
    "home.emptySubTitle": "大切な人を繋いで、記念を共有する為ロックを作成してください。",
    "home.emptySubTitleLink": "もっと見る...",
    "home.buttonCreate": "最初のロックを作成",
    "home.exploreLink": "注目のブログを見る",
    "home.activationTitle": "アカウントアクティベーション必須",
    "home.activationSubTitle": "LoveLockはベータ版であり、まだ公開されていません。",
    "home.activationForm": "このフォームに記入してください。",
    "home.activationGoal": "コンテンツを投稿する前に、アカウントのアクティベーションをリクエストします。",
    "home.supportTitle": "サポートの必要がありませんか。このリンクでお問い合わせください。",
    "home.supportEmail": "電子メール",
    "home.supportOr": " または ",
    "home.supportTelegram": "Telegram",

    "login.noAcc": "アカウントがありませんか？",
    "login.btnRegist": "登録",
    "login.userName": "ユーザー名",
    "login.password": "パスワード",
    "login.rememberMe": "３０日間に忘れないで",
    "login.forgotPass": "パスワードを忘れた場合?",
    "login.btnLogin": "ログイン",
    "login.passReqMes": "この項目は必須である。",
    "login.recoveryLabel": "回復フレーズまたはキー",
    "login.qrCode": "QRコードをスキャン",
    "login.newPassLabel": "新たなパスワード",
    "login.btnBack": "戻る",
    "login.btnRecover": "回復",
    "login.login": "サインイン",

    "regist.userName": "ユーザー名",
    "regist.firstName": "姓",
    "regist.lastName": "名",
    "regist.password": "パスワード",
    "regist.rePassword": "パスワードのご確認",
    "regist.rememberMe": "３０日間に忘れないで",
    "regist.warningText": "ブラウザまたはパスワードマネージャーにパスワードを保持させることをお勧めします。 LoveLockは忘れたパスワードを回復できません。",
    "regist.alreadyAcc": "既存のアカウントがある?",
    "regist.login": "ログイン",
    "regist.next": "次",
    "regist.requiredMes": "この項目は必須である。",
    "regist.userTaken": "このユーザー名はすでに使用されています。",
    "regist.characterCheck": "ユーザー名にスペースや特殊文字を含めることはできません。",
    "regist.passMismatch": "パスワードの不一致",
    "regist.successTitle": "アカウントを作成しました。",
    "regist.successDecs": "以下の秘密の回復フレーズを保存してください。",
    "regist.successNote": "注意：",
    "regist.successNote1": "①上記のフレーズを保存してください。",
    "regist.successNote2": "②誰にも共有しないでください。",
    "regist.successWarning": "「パスワードを忘れた場合」という機能はありません。回復フレーズを保存して秘密にしてください。",
    "regist.successConfirm": "回復フレーズを保存しました。",
    "regist.btnContinue": "続ける",
    "regist.regist": "新たなアカウント作成",

    "header.btnCreate": "作成",
    "header.btnExplore": "もっと見る",
    "header.updateProfile": "プロファイル変更",
    "header.viewRecovery": "回復フレーズ表示",

    "leftmenu.pendingLock": "保留中ロック",
    "leftmenu.folowingLock": "フォロー中ロック",
    "leftmenu.newLock": "新たなロック作成",
    "leftmenu.collection": "コレクション",

    "profile.activationForm": "このフォームに記入してください。",
    "profile.activationGoal": "プロファイルを更新する前に、アカウントのアクティベーションをリクエストします。",
    "profile.userName": "ユーザー名",
    "profile.firstName": "姓",
    "profile.lastName": "名",
    "profile.address": "アドレス ",
    "profile.btnSave": "変更内容を保存",
    "profile.requiredMes": "この項目は必須である。",
    "profile.userTaken": "このユーザー名はすでに使用されています。",
    "profile.characterCheck": "ユーザー名にスペースや特殊文字を含めることはできません。",
    "profile.profile": "プロファイル更新",

    "newLock.newLock": "新たなロック作成",
    "newlock.lockWith": "どなたとロックしたいですか。",
    "newLock.member": "Lovelockメンバー",
    "newLock.crush": "好きな人",
    "newLock.journal": "ジャーナル作成",
    "newLock.msgLockCrush": "貴方のメッセージ",
    "newLock.btnSend": "送信",
    "newLock.btnCover": "カーバ",
    "newLock.activationForm": "このフォームに記入してください。",
    "newLock.activationGoal": "コンテンツを投稿する前に、アカウントのアクティベーションをリクエストします。",
    "newLock.warning": "このロックは公開されます。プライベートロックは次の版でサポートされます。",
    "newLock.btnCreate": "作成 ",
    "newLock.msgJournal": "ジャーナル説明",
    "newLock.journalName": "ジャーナル名",
    "newLock.crushFirstName": "好きな人姓",
    "newLock.crushLastName": "好きな人名",
    "newLock.crushReply": "好きな人返事",
    "newLock.journalSearch": "自分でロックを作成すると、代わりにジャーナルが作成されます。",

    "passPrompt.passTitle": "パスワード確認",
    "passPrompt.pass": "パスワード",
    "passPrompt.forgot": "パスワードを忘れましたか?",
    "passPrompt.remember": "３０日間に忘れないで",
    "passPrompt.btnConfirm": "確認",

    "showMnemonic.recoveryPhrase": "回復フレーズ",
    "showMnemonic.btnOK": "閉じる",
    "showMnemonic.qrCode": "以下のQRコードをスキャンしてください"
}